nomad_camels_driver_mechonics_cu30cl/__init__.py
nomad_camels_driver_mechonics_cu30cl/mechonics_cu30cl.py
nomad_camels_driver_mechonics_cu30cl/mechonics_cu30cl_ophyd.py
nomad_camels_driver_mechonics_cu30cl/servo3ax_wrapper.py
nomad_camels_driver_mechonics_cu30cl-0.1.1.dist-info/licenses/LICENSE.txt
nomad_camels_driver_mechonics_cu30cl-0.1.1.dist-info/METADATA
nomad_camels_driver_mechonics_cu30cl-0.1.1.dist-info/WHEEL
nomad_camels_driver_mechonics_cu30cl-0.1.1.dist-info/top_level.txt
nomad_camels_driver_mechonics_cu30cl-0.1.1.dist-info/RECORD
